handjob/__init__.py
handjob/app.py
handjob-0.2.9.dist-info/LICENSE
handjob-0.2.9.dist-info/METADATA
handjob-0.2.9.dist-info/WHEEL
handjob-0.2.9.dist-info/entry_points.txt
handjob-0.2.9.dist-info/top_level.txt
handjob-0.2.9.dist-info/RECORD
