Metadata-Version: 2.1
Name: handjob
Version: 0.2.9
Summary: Simple handwriting labeling job
Home-page: https://taquy@bitbucket.org/taquy/qt-handwriting-label-job.git
Author: Ta Quy
Author-email: taquy.se@gmail.com
License: MIT
Platform: UNKNOWN
Classifier: Development Status :: 3 - Alpha
Classifier: Intended Audience :: Developers
Classifier: Topic :: Software Development :: Build Tools
Classifier: License :: OSI Approved :: MIT License
Classifier: Programming Language :: Python :: 2
Classifier: Programming Language :: Python :: 2.6
Classifier: Programming Language :: Python :: 2.7
Classifier: Programming Language :: Python :: 3
Classifier: Programming Language :: Python :: 3.2
Classifier: Programming Language :: Python :: 3.3
Classifier: Programming Language :: Python :: 3.4
Requires-Python: >=3.6
Requires-Dist: opencv-python
Requires-Dist: Pillow
